README.txt
setup.py
boois_vali_rule_chker/__init__.py
boois_vali_rule_chker/vali_rule_chker.py
boois_vali_rule_chker.egg-info/PKG-INFO
boois_vali_rule_chker.egg-info/SOURCES.txt
boois_vali_rule_chker.egg-info/dependency_links.txt
boois_vali_rule_chker.egg-info/requires.txt
boois_vali_rule_chker.egg-info/top_level.txt
boois_vali_rule_chker.egg-info/zip-safe